qcarchive_step/__init__.py
qcarchive_step/_version.py
qcarchive_step/metadata.py
qcarchive_step/qcarchive.py
qcarchive_step/qcarchive_parameters.py
qcarchive_step/qcarchive_step.py
qcarchive_step/tk_qcarchive.py
qcarchive_step/data/properties.csv
qcarchive_step/data/references.bib
qcarchive_step-2023.3.30.dist-info/AUTHORS.rst
qcarchive_step-2023.3.30.dist-info/LICENSE
qcarchive_step-2023.3.30.dist-info/METADATA
qcarchive_step-2023.3.30.dist-info/WHEEL
qcarchive_step-2023.3.30.dist-info/entry_points.txt
qcarchive_step-2023.3.30.dist-info/top_level.txt
qcarchive_step-2023.3.30.dist-info/zip-safe
qcarchive_step-2023.3.30.dist-info/RECORD
